[
  {
    "value": "ಬೆಂಗಳೂರು",
    "synonyms": [
      "ಬೆಂಗಳೂರು",
      "ಬ್ಯಾಂಗಲೋರ್",
      "ಬೆಂದಕಾಳೂರು",
      "ಬೆಂಗಳೂರಿನಲ್ಲಿ"
    ]
  },
  {
    "value": "ಮೈಸೂರು",
    "synonyms": [
      "ಮೈಸೂರ್",
      "ಮೈಸೂರು",
      "ಮೈಸೂರಿನಲ್ಲಿ"
    ]
  },
  {
    "value": "ಚಾಮರಾಜನಗರ",
    "synonyms": [
      "ಚಾಮರಾಜನಗರ",
      "ಚಾಮರಾಜನಗರ್",
      "ಚಾಮರಾಜ್ ನಗರ್"
    ]
  },
  {
    "value": "ಮಂಡ್ಯ",
    "synonyms": [
      "ಮಂಡ್ಯ",
      "ಮಂಡಿಯ",
      "ಮಂಡ್ಯಾ"
    ]
  },
  {
    "value": "ಹುಬ್ಬಳ್ಳಿ",
    "synonyms": [
      "ಹುಬ್ಬಳ್ಳಿ",
      "ಹುಬ್ಳಿ"
    ]
  },
  {
    "value": "ಧಾರವಾಡ",
    "synonyms": [
      "ಧಾರವಾಡ",
      "ಧಾರ್ವಾಡ್"
    ]
  },
  {
    "value": "ಕೆಂಗೇರಿ",
    "synonyms": [
      "ಕೆಂಗೇರಿ"
    ]
  },
  {
    "value": "ಅತ್ತಿಬೆಲೆ",
    "synonyms": [
      "ಅತ್ತಿಬೆಲೆ"
    ]
  },
  {
    "value": "ಬಿಡದಿ",
    "synonyms": [
      "ಬಿಡದಿ",
      "ಬಿಡ್ದಿ"
    ]
  },
  {
    "value": "ಪೀಣ್ಯ",
    "synonyms": [
      "ಪೀಣ್ಯ",
      "ಪೀನ್ಯ"
    ]
  },
  {
    "value": "ಕೋಲಾರ್",
    "synonyms": [
      "ಕೋಲಾರ್",
      "ಕೋಲಾರ"
    ]
  },
  {
    "value": "ಶ್ರೀರಂಗಪಟ್ಟಣ",
    "synonyms": [
      "ಶ್ರೀರಂಗಪಟ್ಟಣ",
      "ಶ್ರೀರಂಗಪಟ್ನ",
      "ಶ್ರೀರಂಗಾಪಟ್ನ"
    ]
  },
  {
    "value": "ಪುತ್ತೂರು",
    "synonyms": [
      "ಪುತ್ತೂರು",
      "ಪುತ್ತೂರ್",
      "ಪುಟ್ಟೂರ್",
      "ಪುಟ್ಟೂರು"
    ]
  },
  {
    "value": "ಶಿಮೊಗ್ಗ",
    "synonyms": [
      "ಶಿಮೊಗ್ಗ",
      "ಶಿವಮೊಗ್ಗ",
      "ಶಿಮೊಗ",
      "ಶಿಮೋಗ"
    ]
  },
  {
    "value": "ಕೆಆರ್ ಪೇಟೆ",
    "synonyms": [
      "ಕೆಆರ್ ಪೇಟೆ",
      "ಕೇರಪೇಟೆ"
    ]
  },
  {
    "value": "ಇಲೆಕ್ಟ್ರಾನಿಕ್ ಸಿಟಿ",
    "synonyms": [
      "ಇಲೆಕ್ಟ್ರಾನಿಕ್ ಸಿಟಿ"
    ]
  },
  {
    "value": "ದಾಸೋಹಳ್ಳಿ",
    "synonyms": [
      "ದಾಸೋಹಳ್ಳಿ"
    ]
  },
  {
    "value": "ರಾಮೋಹಳ್ಳಿ",
    "synonyms": [
      "ರಾಮೋಹಳ್ಳಿ"
    ]
  },
  {
    "value": "ಸಿಲ್ಕ್ಬೊರ್ಡು",
    "synonyms": [
      "ಸಿಲ್ಕ್ಬೊರ್ಡು",
      "ಸಿಲ್ಕ್ ಬೋರ್ಡ್"
    ]
  },
  {
    "value": "ಮಳವಳ್ಳಿ",
    "synonyms": [
      "ಮಳವಳ್ಳಿ",
      "ಮಳವಳಿ"
    ]
  },
  {
    "value": "ಕರ್ನಾಟಕ",
    "synonyms": [
      "ಕರ್ನಾಟಕ",
      "ಕರ್ಣಾಟಕ",
      "ಕರ್ನಾಟಕಾ",
      "ಕರ್ನಟಕ"
    ]
  }
]