[
  {
    "value": "इन्फोसिस",
    "synonyms": [
      "इन्फोसिस"
    ]
  },
  {
    "value": "ओला",
    "synonyms": [
      "ओला"
    ]
  },
  {
    "value": "स्वीगजि",
    "synonyms": [
      "स्वीगजि"
    ]
  },
  {
    "value": "झोमाटो",
    "synonyms": [
      "झोमाटो"
    ]
  },
  {
    "value": "उबर",
    "synonyms": [
      "उबर"
    ]
  },
  {
    "value": "ऍमेझॉन",
    "synonyms": [
      "ऍमेझॉन"
    ]
  },
  {
    "value": "उबेर इट्स",
    "synonyms": [
      "उबेर इट्स"
    ]
  },
  {
    "value": "डन्झो",
    "synonyms": [
      "डन्झो"
    ]
  },
  {
    "value": "पिझ्झा हट",
    "synonyms": [
      "पिझ्झा हट"
    ]
  },
  {
    "value": "डॉमिनोस",
    "synonyms": [
      "डॉमिनोस"
    ]
  }
]