[
  {
    "value": "swiggy",
    "synonyms": [
      "swiggy"
    ]
  },
  {
    "value": "zomato",
    "synonyms": [
      "zomato"
    ]
  },
  {
    "value": "ola",
    "synonyms": [
      "ola"
    ]
  },
  {
    "value": "uber",
    "synonyms": [
      "uber"
    ]
  },
  {
    "value": "amazon",
    "synonyms": [
      "amazon",
      "amazon flex"
    ]
  },
  {
    "value": "dunzo",
    "synonyms": [
      "dunzo"
    ]
  },
  {
    "value": "infosys",
    "synonyms": [
      "infosys"
    ]
  },
  {
    "value": "cognizant",
    "synonyms": [
      "cognizant"
    ]
  },
  {
    "value": "wipro",
    "synonyms": [
      "wipro"
    ]
  },
  {
    "value": "tata",
    "synonyms": [
      "tata"
    ]
  }
]