[
  {
    "id": "5835014e-165e-4667-95b2-12d2255cc469",
    "data": [
      {
        "text": "ಅಪ್ಲೈ ಮಾಡಿದ ಕೆಲಸ",
        "userDefined": false
      }
    ],
    "isTemplate": false,
    "count": 0,
    "lang": "de",
    "updated": 0
  },
  {
    "id": "201cbba9-6f6d-41a2-9b9d-dc86f5683cd9",
    "data": [
      {
        "text": "ಅಪ್ಲೈಡ್ ಕೆಲಸ",
        "userDefined": false
      }
    ],
    "isTemplate": false,
    "count": 0,
    "lang": "de",
    "updated": 0
  },
  {
    "id": "822c6e5a-35aa-4bd6-ba6a-cf08946088c2",
    "data": [
      {
        "text": "ಅಪ್ಲೈ ಮಾಡಿದ ಕೆಲಸ ತೋರಿಸು",
        "userDefined": false
      }
    ],
    "isTemplate": false,
    "count": 1,
    "lang": "de",
    "updated": 0
  },
  {
    "id": "0fb32cb7-46e0-437e-adf7-22db12c35f13",
    "data": [
      {
        "text": "ನನ್ನ ಕೆಲಸಗಳನ್ನು ತೋರಿಸು",
        "userDefined": false
      }
    ],
    "isTemplate": false,
    "count": 0,
    "lang": "de",
    "updated": 0
  },
  {
    "id": "693eedd0-a8fa-4e04-ac4b-c05233aad174",
    "data": [
      {
        "text": "ಅನ್ವಯಿಸಿದ ಕೆಲಸಗಳನ್ನು ತೋರಿಸು",
        "userDefined": false
      }
    ],
    "isTemplate": false,
    "count": 0,
    "lang": "de",
    "updated": 0
  },
  {
    "id": "72762c1b-d1bb-4b23-bc5d-202ad8a48876",
    "data": [
      {
        "text": "ಅನ್ವಯಿಸಿದ ಕೆಲಸಗಳನ್ನು ತೋರಿಸಿ",
        "userDefined": false
      }
    ],
    "isTemplate": false,
    "count": 0,
    "lang": "de",
    "updated": 0
  },
  {
    "id": "f6286378-a248-4f9c-9134-2ba6ce16daa5",
    "data": [
      {
        "text": "ಅಪ್ಲೈಡ್ ಕೆಲಸಗಳನ್ನು ತೋರಿಸಿ",
        "userDefined": false
      }
    ],
    "isTemplate": false,
    "count": 0,
    "lang": "de",
    "updated": 0
  },
  {
    "id": "2a3abff1-0892-4411-9005-d4a0f65dade5",
    "data": [
      {
        "text": "ಅಪ್ಲೈಡ್ ಜಾಬ್ಸ್ ತೋರಿಸಿ",
        "userDefined": false
      }
    ],
    "isTemplate": false,
    "count": 0,
    "lang": "de",
    "updated": 0
  },
  {
    "id": "d06870df-58e7-4d5c-972d-fe71bec36c1f",
    "data": [
      {
        "text": "ಅಪ್ಲೈಡ್ ಜಾಬ್ಸ್",
        "userDefined": false
      }
    ],
    "isTemplate": false,
    "count": 0,
    "lang": "de",
    "updated": 0
  },
  {
    "id": "fa5897cf-7768-4a47-a42c-4acc603bbbd8",
    "data": [
      {
        "text": "ನಾನು ಅರ್ಜಿ ಸಲ್ಲಿಸಿದ ಕೆಲಸಗಳನ್ನು ತೋರಿಸಿ",
        "userDefined": false
      }
    ],
    "isTemplate": false,
    "count": 0,
    "lang": "de",
    "updated": 0
  },
  {
    "id": "47a31d19-3ebe-43fe-9ddb-6e2e64dc39e2",
    "data": [
      {
        "text": "ನಾನು ಅರ್ಜಿ ಸಲ್ಲಿಸಿದ ಉದ್ಯೋಗಗಳನ್ನು ತೋರಿಸು",
        "userDefined": false
      }
    ],
    "isTemplate": false,
    "count": 0,
    "lang": "de",
    "updated": 0
  },
  {
    "id": "7aae06b2-8d3e-41d9-a9e3-a0ace0edd6dc",
    "data": [
      {
        "text": "ಅನ್ವಯಿಸಿದ ಕೆಲಸಗಳನ್ನು ನನಗೆ ತೋರಿಸಿ",
        "userDefined": false
      }
    ],
    "isTemplate": false,
    "count": 0,
    "lang": "de",
    "updated": 0
  },
  {
    "id": "9ed8d832-a951-4759-b3a1-cdf4e48c78e5",
    "data": [
      {
        "text": "ನನ್ನ ಅಪ್ಲಿಕೇಶನ್‌ಗಳನ್ನು ತೋರಿಸಿ",
        "userDefined": false
      }
    ],
    "isTemplate": false,
    "count": 0,
    "lang": "de",
    "updated": 0
  },
  {
    "id": "b04d371a-119c-40cf-bd55-9f15a3106e49",
    "data": [
      {
        "text": "ನಾನು ಯಾವ ಉದ್ಯೋಗಗಳಿಗಾಗಿ ಅರ್ಜಿ ಸಲ್ಲಿಸಿದ್ದೇನೆ",
        "userDefined": false
      }
    ],
    "isTemplate": false,
    "count": 0,
    "lang": "de",
    "updated": 0
  }
]